{
    "name": "AmongUs",
    "points": [
        {
            "x": -24.6434326171875,
            "y": -0.0000152587890625
        },
        {
            "x": -19.364707946777345,
            "y": -3.3321380615234377
        },
        {
            "x": -12.721199035644532,
            "y": -2.2014312744140627
        },
        {
            "x": -7.2420501708984379,
            "y": 2.70587158203125
        },
        {
            "x": -1.6527328491210938,
            "y": 8.143463134765625
        },
        {
            "x": 3.1952285766601564,
            "y": 14.256729125976563
        },
        {
            "x": 5.874755859375,
            "y": 21.590988159179689
        },
        {
            "x": 3.5865402221679689,
            "y": 29.650344848632814
        },
        {
            "x": 0.138336181640625,
            "y": 36.63609313964844
        },
        {
            "x": -4.2975616455078129,
            "y": 41.53770446777344
        },
        {
            "x": -9.822738647460938,
            "y": 44.82786560058594
        },
        {
            "x": -15.844566345214844,
            "y": 47.59223937988281
        },
        {
            "x": -22.45330047607422,
            "y": 46.90873718261719
        },
        {
            "x": -25.993148803710939,
            "y": 40.54731750488281
        },
        {
            "x": -28.881126403808595,
            "y": 33.28056335449219
        },
        {
            "x": -29.650161743164064,
            "y": 23.708480834960939
        },
        {
            "x": -29.116348266601564,
            "y": 14.292922973632813
        },
        {
            "x": -26.108566284179689,
            "y": 6.8995513916015629
        },
        {
            "x": -23.0621337890625,
            "y": 4.4092864990234379
        },
        {
            "x": -25.175453186035158,
            "y": 13.276336669921875
        },
        {
            "x": -27.162940979003908,
            "y": 22.905685424804689
        },
        {
            "x": -28.326705932617189,
            "y": 33.21748352050781
        },
        {
            "x": -29.386940002441408,
            "y": 38.32524108886719
        },
        {
            "x": -35.36646270751953,
            "y": 36.24992370605469
        },
        {
            "x": -41.390350341796878,
            "y": 33.10942077636719
        },
        {
            "x": -45.07733917236328,
            "y": 26.644302368164064
        },
        {
            "x": -47.01112365722656,
            "y": 17.684951782226564
        },
        {
            "x": -47.02247619628906,
            "y": 7.1189422607421879
        },
        {
            "x": -46.99909210205078,
            "y": -4.0606842041015629
        },
        {
            "x": -42.80164337158203,
            "y": -11.87066650390625
        },
        {
            "x": -38.73998260498047,
            "y": -20.392898559570314
        },
        {
            "x": -35.09435272216797,
            "y": -27.1619873046875
        },
        {
            "x": -30.441238403320314,
            "y": -33.53538513183594
        },
        {
            "x": -25.268218994140626,
            "y": -38.59568786621094
        },
        {
            "x": -19.711814880371095,
            "y": -42.752655029296878
        },
        {
            "x": -14.601150512695313,
            "y": -47.92546081542969
        },
        {
            "x": -8.426910400390625,
            "y": -49.15904235839844
        },
        {
            "x": -2.9082794189453127,
            "y": -51.29791259765625
        },
        {
            "x": 2.998992919921875,
            "y": -52.40776062011719
        },
        {
            "x": 9.559158325195313,
            "y": -52.34892272949219
        },
        {
            "x": 16.011634826660158,
            "y": -52.30836486816406
        },
        {
            "x": 22.46411895751953,
            "y": -52.26780700683594
        },
        {
            "x": 29.107627868652345,
            "y": -51.137115478515628
        },
        {
            "x": 35.54901885986328,
            "y": -48.98316955566406
        },
        {
            "x": 41.218711853027347,
            "y": -45.902923583984378
        },
        {
            "x": 45.52216339111328,
            "y": -39.600189208984378
        },
        {
            "x": 50.84699249267578,
            "y": -35.40138244628906
        },
        {
            "x": 49.86205291748047,
            "y": -29.624969482421876
        },
        {
            "x": 45.045188903808597,
            "y": -26.214218139648439
        },
        {
            "x": 39.018898010253909,
            "y": -24.668487548828126
        },
        {
            "x": 37.275901794433597,
            "y": -15.458694458007813
        },
        {
            "x": 36.62328338623047,
            "y": -3.9480743408203127
        },
        {
            "x": 36.23387908935547,
            "y": 7.1881256103515629
        },
        {
            "x": 42.87737274169922,
            "y": 8.318817138671875
        },
        {
            "x": 48.237266540527347,
            "y": 12.403961181640625
        },
        {
            "x": 52.977516174316409,
            "y": 18.498916625976564
        },
        {
            "x": 49.829368591308597,
            "y": 21.136062622070314
        },
        {
            "x": 43.729515075683597,
            "y": 23.107650756835939
        },
        {
            "x": 37.30651092529297,
            "y": 23.235244750976564
        },
        {
            "x": 30.854042053222658,
            "y": 23.194686889648439
        },
        {
            "x": 24.512672424316408,
            "y": 24.989334106445314
        },
        {
            "x": 18.45325469970703,
            "y": 27.429977416992189
        },
        {
            "x": 12.855766296386719,
            "y": 27.534957885742189
        }
    ],
    "color": {
        "r": 1.0,
        "g": 0.0,
        "b": 0.0,
        "a": 1.0
    }
}