{
    "name": "AmongUs",
    "points": [
        {
            "x": -27.567150115966798,
            "y": 0.0
        },
        {
            "x": -22.743846893310548,
            "y": -3.579437255859375
        },
        {
            "x": -17.3524169921875,
            "y": -5.5606842041015629
        },
        {
            "x": -11.625335693359375,
            "y": -7.6732330322265629
        },
        {
            "x": -6.489662170410156,
            "y": -7.91900634765625
        },
        {
            "x": -1.6954269409179688,
            "y": -5.49578857421875
        },
        {
            "x": 2.9771652221679689,
            "y": 1.277130126953125
        },
        {
            "x": 6.036415100097656,
            "y": 9.50982666015625
        },
        {
            "x": 6.2827301025390629,
            "y": 17.758010864257814
        },
        {
            "x": 4.9590606689453129,
            "y": 27.054397583007814
        },
        {
            "x": 2.8619232177734377,
            "y": 34.19989013671875
        },
        {
            "x": -2.3039093017578127,
            "y": 39.02723693847656
        },
        {
            "x": -7.561485290527344,
            "y": 38.14503479003906
        },
        {
            "x": -13.347343444824219,
            "y": 37.291961669921878
        },
        {
            "x": -18.22021484375,
            "y": 33.915435791015628
        },
        {
            "x": -23.470584869384767,
            "y": 30.831008911132814
        },
        {
            "x": -28.492889404296876,
            "y": 28.077133178710939
        },
        {
            "x": -32.18684005737305,
            "y": 20.459716796875
        },
        {
            "x": -33.30375671386719,
            "y": 12.640121459960938
        },
        {
            "x": -32.02674865722656,
            "y": 5.018218994140625
        },
        {
            "x": -28.63788604736328,
            "y": 3.0025482177734377
        },
        {
            "x": -33.387062072753909,
            "y": 6.763702392578125
        },
        {
            "x": -38.52355194091797,
            "y": 4.4857025146484379
        },
        {
            "x": -44.14069366455078,
            "y": 0.8696136474609375
        },
        {
            "x": -48.75746154785156,
            "y": -5.9063873291015629
        },
        {
            "x": -48.606136322021487,
            "y": -14.660476684570313
        },
        {
            "x": -46.313987731933597,
            "y": -23.104934692382814
        },
        {
            "x": -43.816280364990237,
            "y": -31.160537719726564
        },
        {
            "x": -40.00254821777344,
            "y": -38.74363708496094
        },
        {
            "x": -35.10908508300781,
            "y": -43.46940612792969
        },
        {
            "x": -29.623931884765626,
            "y": -46.16197204589844
        },
        {
            "x": -24.044265747070314,
            "y": -47.884368896484378
        },
        {
            "x": -18.189006805419923,
            "y": -50.88075256347656
        },
        {
            "x": -12.201896667480469,
            "y": -53.56416320800781
        },
        {
            "x": -6.753265380859375,
            "y": -54.189208984375
        },
        {
            "x": -1.9442672729492188,
            "y": -51.11640930175781
        },
        {
            "x": 3.3283233642578127,
            "y": -48.75569152832031
        },
        {
            "x": 9.314407348632813,
            "y": -46.54765319824219
        },
        {
            "x": 14.792793273925782,
            "y": -42.73114013671875
        },
        {
            "x": 19.99884033203125,
            "y": -37.413787841796878
        },
        {
            "x": 24.872886657714845,
            "y": -31.4803466796875
        },
        {
            "x": 29.948394775390626,
            "y": -26.386367797851564
        },
        {
            "x": 34.82244873046875,
            "y": -20.45294189453125
        },
        {
            "x": 39.696495056152347,
            "y": -14.519485473632813
        },
        {
            "x": 44.63990020751953,
            "y": -8.485504150390625
        },
        {
            "x": 48.46051025390625,
            "y": -1.1077728271484376
        },
        {
            "x": 51.242530822753909,
            "y": 6.6526031494140629
        },
        {
            "x": 50.861610412597659,
            "y": 14.76861572265625
        },
        {
            "x": 47.768829345703128,
            "y": 20.94287109375
        },
        {
            "x": 42.17572021484375,
            "y": 20.177978515625
        },
        {
            "x": 36.84901428222656,
            "y": 18.692535400390626
        },
        {
            "x": 31.97496795654297,
            "y": 12.75909423828125
        },
        {
            "x": 27.100921630859376,
            "y": 6.8256378173828129
        },
        {
            "x": 23.707138061523439,
            "y": 6.432342529296875
        },
        {
            "x": 23.053123474121095,
            "y": 13.841567993164063
        },
        {
            "x": 21.51080322265625,
            "y": 22.411300659179689
        },
        {
            "x": 18.333106994628908,
            "y": 30.324661254882814
        },
        {
            "x": 22.979095458984376,
            "y": 35.92750549316406
        },
        {
            "x": 26.375625610351564,
            "y": 43.113800048828128
        },
        {
            "x": 23.445571899414064,
            "y": 45.810791015625
        },
        {
            "x": 18.02135467529297,
            "y": 43.45072937011719
        },
        {
            "x": 12.500175476074219,
            "y": 41.10523986816406
        },
        {
            "x": 7.547523498535156,
            "y": 35.386260986328128
        }
    ],
    "color": {
        "r": 1.0,
        "g": 0.0,
        "b": 0.0,
        "a": 1.0
    }
}