{
    "name": "Line",
    "points": [
        {
            "x": -50.000247955322269,
            "y": -0.0009765625
        },
        {
            "x": -48.412254333496097,
            "y": -1.794921875
        },
        {
            "x": -46.82426071166992,
            "y": -3.5908203125
        },
        {
            "x": -45.23626708984375,
            "y": -5.3857421875
        },
        {
            "x": -43.64827346801758,
            "y": -7.181640625
        },
        {
            "x": -42.060279846191409,
            "y": -8.9755859375
        },
        {
            "x": -40.472286224365237,
            "y": -10.7705078125
        },
        {
            "x": -38.88429641723633,
            "y": -12.56640625
        },
        {
            "x": -37.296302795410159,
            "y": -14.361328125
        },
        {
            "x": -35.70830535888672,
            "y": -16.1552734375
        },
        {
            "x": -34.12031555175781,
            "y": -17.951171875
        },
        {
            "x": -32.53232192993164,
            "y": -19.74609375
        },
        {
            "x": -30.94432830810547,
            "y": -21.541015625
        },
        {
            "x": -29.356334686279298,
            "y": -23.3359375
        },
        {
            "x": -27.768342971801759,
            "y": -25.130859375
        },
        {
            "x": -26.180349349975587,
            "y": -26.9267578125
        },
        {
            "x": -24.592355728149415,
            "y": -28.720703125
        },
        {
            "x": -23.004362106323243,
            "y": -30.515625
        },
        {
            "x": -21.416370391845704,
            "y": -32.3115234375
        },
        {
            "x": -19.82837677001953,
            "y": -34.1064453125
        },
        {
            "x": -18.24038314819336,
            "y": -35.9013671875
        },
        {
            "x": -16.652389526367189,
            "y": -37.6962890625
        },
        {
            "x": -15.064399719238282,
            "y": -39.4912109375
        },
        {
            "x": -13.47640609741211,
            "y": -41.287109375
        },
        {
            "x": -11.888412475585938,
            "y": -43.0810546875
        },
        {
            "x": -10.300418853759766,
            "y": -44.8759765625
        },
        {
            "x": -8.71242904663086,
            "y": -46.671875
        },
        {
            "x": -7.1244354248046879,
            "y": -48.466796875
        },
        {
            "x": -5.53643798828125,
            "y": -50.26171875
        },
        {
            "x": -3.9527435302734377,
            "y": -40.77734375
        },
        {
            "x": -2.3708763122558595,
            "y": -26.4873046875
        },
        {
            "x": -0.7890090942382813,
            "y": -12.1982421875
        },
        {
            "x": 0.7928581237792969,
            "y": 2.0908203125
        },
        {
            "x": 2.3747291564941408,
            "y": 16.3798828125
        },
        {
            "x": 3.956592559814453,
            "y": 30.669921875
        },
        {
            "x": 5.538459777832031,
            "y": 44.958984375
        },
        {
            "x": 7.1239471435546879,
            "y": 49.73828125
        },
        {
            "x": 8.71194076538086,
            "y": 47.943359375
        },
        {
            "x": 10.299934387207032,
            "y": 46.1474609375
        },
        {
            "x": 11.887928009033204,
            "y": 44.353515625
        },
        {
            "x": 13.47592544555664,
            "y": 42.5576171875
        },
        {
            "x": 15.063915252685547,
            "y": 40.7626953125
        },
        {
            "x": 16.651905059814454,
            "y": 38.9677734375
        },
        {
            "x": 18.23990249633789,
            "y": 37.1728515625
        },
        {
            "x": 19.827892303466798,
            "y": 35.3779296875
        },
        {
            "x": 21.415882110595704,
            "y": 33.5830078125
        },
        {
            "x": 23.00387954711914,
            "y": 31.7880859375
        },
        {
            "x": 24.591869354248048,
            "y": 29.9931640625
        },
        {
            "x": 26.179866790771486,
            "y": 28.197265625
        },
        {
            "x": 27.76784896850586,
            "y": 26.40234375
        },
        {
            "x": 29.355846405029298,
            "y": 24.6083984375
        },
        {
            "x": 30.943843841552736,
            "y": 22.8125
        },
        {
            "x": 32.53183364868164,
            "y": 21.017578125
        },
        {
            "x": 34.11983108520508,
            "y": 19.2216796875
        },
        {
            "x": 35.707820892333987,
            "y": 17.427734375
        },
        {
            "x": 37.29581832885742,
            "y": 15.6328125
        },
        {
            "x": 38.88380813598633,
            "y": 13.8369140625
        },
        {
            "x": 40.471797943115237,
            "y": 12.0419921875
        },
        {
            "x": 42.05979537963867,
            "y": 10.248046875
        },
        {
            "x": 43.64778518676758,
            "y": 8.4521484375
        },
        {
            "x": 45.235782623291019,
            "y": 6.6572265625
        },
        {
            "x": 46.82377243041992,
            "y": 4.8623046875
        },
        {
            "x": 48.41176986694336,
            "y": 3.0673828125
        },
        {
            "x": 49.999759674072269,
            "y": 1.2724609375
        }
    ],
    "color": {
        "r": 0.0,
        "g": 0.36220645904541018,
        "b": 1.0,
        "a": 1.0
    }
}